{"xSE2B0iUpAWCvonhJlPthA==":"worked-logo.svg","MJRlBVsXyA73oidZeslyEw==":"amznworked.jpg","+xTNLDoIbb5T6BzHrpx0WA==":"amznworked.png","zRmy/0TqWS0ozJLxpExZ0A==":"bmcc-nyc-2024.jpg","H4oGl67Zw8+Y5fYmNYOyGg==":"bmcc-nyc-2026.jpg","jo0KUdeZKZpdvSaaR2HFCQ==":"carley.jpeg","D9MaMmQ++q6W2Fp6F6d6Yg==":"kathy.jpeg","mkv00uZGXStEY17a4s6ZGQ==":"arleene.jpeg","87scP7t1zkvqAJ3CkILxeA==":"drwei.jpg","kl4m+UkuBwa9gCyC5Yi7cw==":"1280928-th1.jpg","UoGPhTXFCPtLr4A66Otzug==":"img.jpg","bU+BCB4d7rHVmcowK0IjBw==":"lauren.jpeg","czwFlGIAV48k/OpdTrCW0w==":"screenshot-2024-08-27-at-8.52.43pm.png","5hwnah2iC1tdz9T+8U4igg==":"screenshot-2024-08-27-at-8.52.52pm.png","3Q/77CgVUBB94IXYsDm0mQ==":"screenshot-2024-08-27-at-8.53.03pm.png","aSsUvdHxTFzjgcjK8mXItg==":"badge.png","7AaRdrOMHCOdGCHlOLDJ5w==":"generative-ai-160x160.png","rr1RrXKKZAg4xVCwruLz4w==":"coding-with-ai-160x160.png","xvfTY/IPgd9smfyGO2L16A==":"chatbot-160x160.png","CCx5FqAf6houbu4zdmpOLg==":"machine-learning-models-160x160.png","DSHTHZ5TXkBI9WR8bVcrSQ==":"hackathon-160x160.png","6PjFrB7cVTOSL2PNTdgpsQ==":"ai-externship-160x160.png","Lac45BCWh3lg9+JBCK5JQA==":"ai-externship-mvp-160x160.png","6ZDf23YUD+0Q/1FOecBXsQ==":"screenshot%202024-08-27%20at%208.58.05%E2%80%AFpm-1160x755.png","d3bvdNFDyo/jAWyPWmpB4A==":"output-1256x916.png","1huOdHRkQ5NZvTGaJaj0Ww==":"amznworked-1920x1080.jpg","QAEGfjx7/YYuAmJrb0Pq1Q==":"bmcc%20-%20nyc%20-%202024%20-%2015-646x431.jpg","uIEcioWYH4X/HaMPMH2Vew==":"bmcc%20-%20nyc%20-%202024%20-%2025-646x431.jpg","c6bRqzgvFPqxQmfZmgqHNw==":"bmcc%20-%20nyc%20-%202024%20-%2027-646x431.jpg","mgpp8BNQVOuUEZuCeHLT/w==":"bmcc%20-%20nyc%20-%202024%20-%2032-646x431.jpg","N8gCIZeHpvNak1yF8XOXuA==":"bmcc%20-%20nyc%20-%202024%20-%2035-646x431.jpg","balN1YZbbZs+D5BX6Q4asw==":"bmcc%20-%20nyc%20-%202024%20-%2049-646x431.jpg","2E969EcqyBOXEh+WVTCr6w==":"bmcc%20-%20nyc%20-%202024%20-%2051-646x431.jpg","YqwScKFgRn9/Ffnifky9vw==":"bmcc%20-%20nyc%20-%202024%20-%2061-646x431.jpg"}